simple_gpu_scheduler/__init__.py
simple_gpu_scheduler/command_line.py
simple_gpu_scheduler/hypersearch.py
simple_gpu_scheduler/scheduler.py
simple_gpu_scheduler-0.1.4.dist-info/LICENSE
simple_gpu_scheduler-0.1.4.dist-info/METADATA
simple_gpu_scheduler-0.1.4.dist-info/WHEEL
simple_gpu_scheduler-0.1.4.dist-info/entry_points.txt
simple_gpu_scheduler-0.1.4.dist-info/top_level.txt
simple_gpu_scheduler-0.1.4.dist-info/RECORD
