Metadata-Version: 2.1
Name: simple-gpu-scheduler
Version: 0.1.4
Summary: A simple scheduler for running commands on multiple GPUs.
Home-page: https://github.com/ExpectationMax/simple_gpu_scheduler
Author: Max Horn
Author-email: maexlich@gmail.com
License: UNKNOWN
Platform: UNKNOWN
Classifier: Programming Language :: Python :: 3 :: Only
Classifier: Programming Language :: Python :: 3.6
Classifier: License :: OSI Approved :: GNU General Public License v3 (GPLv3)
Requires-Python: >3.6
